differences/__init__.py
differences/_version.py
differences/attgt/__init__.py
differences/attgt/aggregate.py
differences/attgt/attgt.py
differences/attgt/attgt_cal.py
differences/attgt/difference.py
differences/attgt/mboot.py
differences/attgt/utility.py
differences/datasets/__init__.py
differences/datasets/generate_data.py
differences/datasets/load_data.py
differences/datasets/me.csv
differences/datasets/mpdta.csv
differences/datasets/rcs-multi_period.csv
differences/datasets/rcs-two_periods.csv
differences/datasets/se.csv
differences/did/__init__.py
differences/did/att_if.py
differences/did/did_cal.py
differences/did/pscore_cal.py
differences/did/utility.py
differences/tools/__init__.py
differences/tools/panel_utility.py
differences/tools/panel_validation.py
differences/tools/relative_periods.py
differences/tools/utility.py
differences-0.2.0.dist-info/LICENSE.md
differences-0.2.0.dist-info/METADATA
differences-0.2.0.dist-info/WHEEL
differences-0.2.0.dist-info/top_level.txt
differences-0.2.0.dist-info/RECORD
