Metadata-Version: 2.1
Name: differences
Version: 0.2.0
Summary: difference-in-differences estimation and inference in Python
Author-email: Bernardo Dionisi <bernardo.dionisi@gmail.com>
License: GPLv3
Project-URL: Homepage, https://github.com/bernardodionisi/differences
Project-URL: Source, https://github.com/bernardodionisi/differences
Project-URL: Issues, https://github.com/bernardodionisi/differences/issues
Project-URL: Documentation, https://bernardodionisi.github.io/differences/latest/
Keywords: did,difference-in-differences,panel data,econometrics,causal inference
Classifier: Intended Audience :: Science/Research
Classifier: Intended Audience :: Education
Classifier: Intended Audience :: Developers
Classifier: Topic :: Software Development :: Libraries :: Python Modules
Classifier: License :: OSI Approved :: MIT License
Classifier: Programming Language :: Python :: 3.9
Classifier: Programming Language :: Python :: 3.10
Classifier: Programming Language :: Python :: 3.11
Classifier: Programming Language :: Python :: 3.12
Classifier: Operating System :: OS Independent
Requires-Python: >=3.9
License-File: LICENSE.md
Requires-Dist: numpy >=1.19
Requires-Dist: scipy >=1.8
Requires-Dist: pandas >=1.2
Requires-Dist: linearmodels >=4.25
Requires-Dist: statsmodels <1.0,>=0.13
Requires-Dist: formulaic <0.4.0,>=0.3.4
Requires-Dist: tqdm >=4.64.1
Requires-Dist: joblib >=1.2.0
Requires-Dist: typing-extensions >=4.0.0
